MANIFEST.in
setup.py
colorguard/__init__.py
colorguard/bits.py
colorguard/flags.py
colorguard.egg-info/PKG-INFO
colorguard.egg-info/SOURCES.txt
colorguard.egg-info/dependency_links.txt
colorguard.egg-info/top_level.txt