Metadata-Version: 1.0
Name: colorguard
Version: 0.4
Summary: Better bit manipulation that allows indexing, and automatic bit flags.
Home-page: http://github.com/reshanie/colorguard
Author: Patrick Dill
Author-email: jamespatrickdill@gmail.com
License: MIT
Platform: UNKNOWN
